sarthi_sandeshrathod09/__init__.py
sarthi_sandeshrathod09/app.py
sarthi-0.0.1.dist-info/LICENSE
sarthi-0.0.1.dist-info/METADATA
sarthi-0.0.1.dist-info/WHEEL
sarthi-0.0.1.dist-info/top_level.txt
sarthi-0.0.1.dist-info/RECORD
