Metadata-Version: 2.1
Name: sarthi
Version: 0.0.1
Summary: Sarthi B2B AES encrypt cryptodome for SSO
Author-email: sandesh rathod <sandeshrathod09@gmail.com>
License: MIT License        
Project-URL: Homepage, https://github.com/pypa/sandeshrathod09/sarthi
Project-URL: Bug Tracker, https://github.com/pypa/sandeshrathod09/sarthi/issues
Classifier: Programming Language :: Python :: 3
Classifier: License :: OSI Approved :: MIT License
Classifier: Operating System :: OS Independent
Requires-Python: >=3.7
License-File: LICENSE
